source/hardware/fast_rep.sv
module fast_repetition (
    input       sys_clk,
    input       reset_n,
    input       clear,
    input       valid,
    input       [FIELD_SIZE-1:0] field,
    output      [FIELD_SIZE-1:0]  rep_rate
);
    parameter FIELD_SIZE = 16;
    parameter REPETION_THRESHOLD = 1;
    parameter N_CLR = 3;

    localparam N_REP = 1; //$clog2(REPETION_THRESHOLD);
    localparam SIZE = 2 ** FIELD_SIZE;
    localparam WORD_SIZE = N_REP * N_CLR;
    localparam INITIAL_MASK = (1 << N_REP) - 1;

    logic [WORD_SIZE-1:0] mem [SIZE];
    logic [WORD_SIZE-1:0] mem_out;
    logic [WORD_SIZE-1:0] mem_in;
    logic [WORD_SIZE-1:0] mask;
    logic [WORD_SIZE-1:0] rep_incr;
    logic [WORD_SIZE-1:0] threshold;
    logic threshold_reached;
    
    logic [FIELD_SIZE-1:0] raddr;
    logic [FIELD_SIZE-1:0] waddr;
    logic [FIELD_SIZE-1:0] count;
    logic raddr_valid, out_valid, count_incr, bypass;
    logic [2:0] clear_d;

    assign threshold_reached = (mem_out & mask) == threshold;
    assign mem_in = threshold_reached ? threshold : (mem_out + rep_incr) & mask;

    assign count_incr = (threshold_reached | bypass) & out_valid;
    assign rep_rate = count;

    `ifdef __ICARUS__
    initial begin
        for (int i = 0; i < SIZE; i++)
            mem[i] = 0;
    end
    `endif
    
    always @(posedge sys_clk, negedge reset_n) begin
        if (~reset_n) begin
            raddr <= 0;
            waddr <= 0;
            count <= 0;
            raddr_valid <= 0;
            out_valid <= 0;
            mem_out <= 0;
            mask <= INITIAL_MASK;
            rep_incr <= 1;
            threshold <= REPETION_THRESHOLD;
            bypass <= 0;
            clear_d <= 0;
        end 
        else begin
            clear_d <= {clear_d[1:0], clear};
            if (clear_d[0]) begin
                mask <= {mask[WORD_SIZE-N_REP-1:0], mask[WORD_SIZE-1:WORD_SIZE-N_REP]};     
                rep_incr <= {rep_incr[WORD_SIZE-N_REP-1:0], rep_incr[WORD_SIZE-1:WORD_SIZE-N_REP]};   
                threshold <= {threshold[WORD_SIZE-N_REP-1:0], threshold[WORD_SIZE-1:WORD_SIZE-N_REP]};   
            end

            if (valid) begin
                raddr <= field;
                raddr_valid <= 1;
            end 
            else begin
                raddr_valid <= 0;
            end
            
            if (raddr_valid) begin
                waddr <= raddr;
                mem_out <= mem[raddr];
                out_valid <= 1;
                bypass <= (waddr == raddr) & out_valid;
            end
            else begin
                out_valid <= 0;
                bypass <= 0;
            end
            
            if (out_valid) begin
                mem[waddr] <= mem_in;
            end
            count <= (clear_d[2] ? 0 : count) + count_incr;
        end
    end
endmodule

module windowing (
    input       sys_clk,
    input       reset_n,
    input       valid,
    input       [FIELD_SIZE-1:0] field,
    output reg  found
);
    parameter FIELD_SIZE = 16;
    parameter WINDOW_SIZE = 32;         // Must be power of 2
    parameter THRESHOLD = 5;

    localparam N_WND = $clog2(WINDOW_SIZE);

    logic [N_WND-1:0] window_count;
    logic [FIELD_SIZE-1:0] rep_rate;
    logic clear;
    
    assign clear = window_count == 0;
    
    always @(posedge sys_clk or negedge reset_n) begin
        if (~reset_n) begin
            window_count <= 0;
            found <= 0;
        end
        else begin
            window_count <= window_count + 1;
            found <= rep_rate >= THRESHOLD;
        end
    end

    fast_repetition #(FIELD_SIZE) rep0(
        .sys_clk(sys_clk),
        .reset_n(reset_n),
        .clear(clear),
        .valid(valid),
        .field(field),
        .rep_rate(rep_rate)
    );


endmodule

source/hardware/test/repetition_test.sv
module repetition_test ();
    localparam FIELD_SIZE = 16;

    logic clk = 0;
    logic reset_n = 0;

    logic valid = 0, ready, clear = 0;

    logic [FIELD_SIZE-1:0] field ;
    logic [FIELD_SIZE-1:0] rep_rate;
    logic [FIELD_SIZE-1:0] nreps;
    
    always #5 clk = ~clk;

    /* reg [15:0] data [0:3]; */
    /* int i; */
    /* initial begin */
    /*     $readmemh("reptest_data", data); */
    /*     for (i=0; i < 4; i=i+1) */
    /*         $display("%d:%h",i,data[i]); */
    /* end */

    integer f, rc, line;
    string filename;
    int dump = 0;
    initial begin
        if(!$value$plusargs("FN=%s", filename))
            $warning(1);

        if(!$value$plusargs("dump=%d", dump))
            $warning(1);

        if (dump) begin
            $dumpfile("repetition_test.vcd");
            $dumpvars(0,repetition_test);
        end
        f = $fopen(filename, "r");
        rc = $fscanf(f, "%d\n", nreps);
        if (rc != 1) begin 
            $display("fscanf failed");
        end
        #25 reset_n = 1;
    end

    int endticks = 0;
    always @(negedge clk) begin
        if ($feof(f)) begin
            valid = 0;
            endticks += 1;
            if (endticks == 4)
                if(rep_rate == nreps) begin
                    $display("Passed, %d reps found %d expected", rep_rate, nreps);
                    $finish(0);
                end
                else begin 
                    $display("Failed, %d reps found %d expected", rep_rate, nreps);
                    $finish(1);
                end
        end
        else if(ready) begin
            rc = $fscanf(f, "%d\n", line);
            if (rc != 1) begin 
                $display("fscanf failed");
            end
            valid = 1;
            field  = line;
            if (line < 0) begin
                clear = 1;
                rc = $fscanf(f, "%d\n", field);
                if (rc != 1) begin 
                    $display("fscanf failed");
                end
            end
            else begin 
                clear = 0;
                field = line;

            end
        end
        /* $display("ready:%x", ready); */
        /* $display("%x,%d,%d", field[FIELD_SIZE-1:0], rep_rate[FIELD_SIZE-1:0], valid); */
        /* $display("rr:%d\n", rep_rate); */

    end

    fast_repetition #(FIELD_SIZE) rep0(
        .sys_clk(clk),
        .reset_n(reset_n),
        .clear(clear),
        .valid(valid),
        .field(field),
        .rep_rate(rep_rate)
        /* .ready(ready) */
    );
    assign ready = reset_n;


endmodule

source/hardware/test/repetition_test.vcd
$date
	Thu Dec 12 16:14:35 2019
$end
$version
	Icarus Verilog
$end
$timescale
	1s
$end
$scope module repetition_test $end
$var wire 1 ! ready $end
$var wire 16 " rep_rate [15:0] $end
$var reg 1 # clear $end
$var reg 1 $ clk $end
$var reg 16 % field [15:0] $end
$var reg 16 & nreps [15:0] $end
$var reg 1 ' reset_n $end
$var reg 1 ( valid $end
$var integer 32 ) dump [31:0] $end
$var integer 32 * endticks [31:0] $end
$var integer 32 + f [31:0] $end
$var integer 32 , line [31:0] $end
$var integer 32 - rc [31:0] $end
$scope module rep0 $end
$var wire 1 # clear $end
$var wire 1 . count_incr $end
$var wire 16 / field [15:0] $end
$var wire 16 0 rep_rate [15:0] $end
$var wire 1 ' reset_n $end
$var wire 1 $ sys_clk $end
$var wire 1 ( valid $end
$var wire 1 1 threshold_reached $end
$var wire 3 2 mem_in [2:0] $end
$var reg 1 3 bypass $end
$var reg 3 4 clear_d [2:0] $end
$var reg 16 5 count [15:0] $end
$var reg 3 6 mask [2:0] $end
$var reg 3 7 mem_out [2:0] $end
$var reg 1 8 out_valid $end
$var reg 16 9 raddr [15:0] $end
$var reg 1 : raddr_valid $end
$var reg 3 ; rep_incr [2:0] $end
$var reg 3 < threshold [2:0] $end
$var reg 16 = waddr [15:0] $end
$upscope $end
$upscope $end
$enddefinitions $end
#0
$dumpvars
bx =
bx <
bx ;
x:
bx 9
x8
bx 7
bx 6
bx 5
bx 4
x3
bx 2
x1
bx 0
bx /
x.
b1 -
bx ,
b10000000000000000000000000000011 +
b0 *
b1 )
0(
0'
b10 &
bx %
0$
0#
bx "
0!
$end
#5
b1 2
01
0.
b0 4
03
b1 <
b1 ;
b1 6
b0 7
08
0:
b0 "
b0 0
b0 5
b0 =
b0 9
1$
#10
0$
#15
1$
#20
0$
#25
1$
1!
1'
#30
1#
b1 %
b1 /
1(
b11111111111111111111111111111111 ,
0$
#35
1:
b1 9
b1 4
1$
#40
0#
b0 %
b0 /
b0 ,
0$
#45
x.
b0x0 2
x1
18
bx 7
b1 =
b0 9
b10 <
b10 ;
b10 6
b10 4
1$
#50
b1 %
b1 /
b1 ,
0$
#55
bx "
bx 0
bx 5
b0 =
b1 9
b100 4
1$
#60
b0 %
b0 /
b0 ,
0$
#65
b0x0 7
b1 =
b0 9
b0 4
1$
#70
b1 *
0(
0$
#75
b0 =
0:
1$
#80
b10 *
0$
#85
0.
08
1$
#90
b11 *
0$
#95
1$
#100
b100 *
0$
